devblaze/__init__.py
devblaze/app.py
devblaze/main.py
devblaze/textual_utils/__init__.py
devblaze/textual_utils/constants.py
devblaze/textual_utils/containers/__init__.py
devblaze/textual_utils/containers/base.py
devblaze/textual_utils/containers/project.py
devblaze/textual_utils/containers/use_service.py
devblaze/textual_utils/modals/__init__.py
devblaze/textual_utils/modals/success.py
devblaze/textual_utils/screens/__init__.py
devblaze/textual_utils/screens/base_app.py
devblaze/textual_utils/screens/project.py
devblaze/textual_utils/screens/use_service.py
devblaze/textual_utils/static/demo.css
devblaze/textual_utils/static/modals.css
devblaze/textual_utils/static/project-info.css
devblaze/textual_utils/static/test.css
devblaze/textual_utils/static/test_screen.css
devblaze/textual_utils/static/use-service.css
devblaze/textual_utils/widgets/__init__.py
devblaze/textual_utils/widgets/inputs.py
devblaze/textual_utils/widgets/radio_sets.py
devblaze-0.0.5.dist-info/METADATA
devblaze-0.0.5.dist-info/WHEEL
devblaze-0.0.5.dist-info/entry_points.txt
devblaze-0.0.5.dist-info/licenses/LICENSE
devblaze-0.0.5.dist-info/RECORD
