Metadata-Version: 2.1
Name: devblaze
Version: 0.0.5
Summary: A tool for creating and managing development and production environments.
Project-URL: Homepage, https://github.com/godd0t/devblaze
Author-email: Lirim Shala <lirrishala@gmail.com>
License: MIT
License-File: LICENSE
Classifier: Development Status :: 1 - Planning
Classifier: Environment :: Web Environment
Classifier: Framework :: Django :: 4.2
Classifier: Intended Audience :: Developers
Classifier: License :: OSI Approved :: MIT License
Classifier: Operating System :: OS Independent
Classifier: Programming Language :: Python :: 3.11
Classifier: Topic :: Software Development :: Libraries :: Python Modules
Classifier: Topic :: Software Development :: Version Control :: Git
Classifier: Topic :: System :: Logging
Classifier: Topic :: Utilities
Requires-Python: >=3.10
Requires-Dist: cookiecutter==2.1.1
Requires-Dist: textual==0.24.1
Provides-Extra: dev
Requires-Dist: black==23.3.0; extra == 'dev'
Requires-Dist: build==0.10.0; extra == 'dev'
Requires-Dist: ruff==0.0.267; extra == 'dev'
Requires-Dist: twine==4.0.2; extra == 'dev'
